github_storage/__init__.py
github_storage/github_storage.py
github_storage-0.1.0.dist-info/METADATA
github_storage-0.1.0.dist-info/WHEEL
github_storage-0.1.0.dist-info/entry_points.txt
github_storage-0.1.0.dist-info/top_level.txt
github_storage-0.1.0.dist-info/RECORD
