Metadata-Version: 2.1
Name: github_storage
Version: 0.1.0
Summary: A Python package that uses GitHub repositories as a database for storing and retrieving data.
Home-page: https://github.com/ahson01/github_storage
Author: Ahson H.
Author-email: ahson01@proton.me
Classifier: Programming Language :: Python :: 3
Classifier: License :: OSI Approved :: MIT License
Classifier: Operating System :: OS Independent
Requires-Python: >=3.6
Requires-Dist: PyGithub
Requires-Dist: pycryptodome
